masterlog/__init__.py
masterlog/log.py
masterlog-0.1.4.dist-info/LICENSE
masterlog-0.1.4.dist-info/METADATA
masterlog-0.1.4.dist-info/WHEEL
masterlog-0.1.4.dist-info/top_level.txt
masterlog-0.1.4.dist-info/RECORD
