Metadata-Version: 2.1
Name: masterlog
Version: 0.1.4
Summary: Versatile Python logging package with source management.
Home-page: https://github.com/sergey-hovhannisyan/masterlog
Author: Sergey Hovhannisyan
License: Apache License 2.0
Classifier: Programming Language :: Python :: 3
Classifier: License :: OSI Approved :: Apache Software License
Classifier: Operating System :: OS Independent
License-File: LICENSE
